<?xml version="1.0"?>
<karaoke length="250984">
  <lines>
    <line words="&#x5168;&#x901F;&#x529B;&#x3067;&#x8D70;&#x3063;&#x3066;&#x308B;&#x306E;&#x8AB0;&#xFF1F;" start="9988" length="7683">
      <subtitles>
        <subtitle lang="en" line="Who is galloping?"/>
      <subtitle lang="us" line="Who is galloping?"/><subtitle lang="au" line="Who is galloping?"/><subtitle lang="bz" line="Who is galloping?"/><subtitle lang="jm" line="Who is galloping?"/><subtitle lang="tt" line="Who is galloping?"/><subtitle lang="gy" line="Who is galloping?"/><subtitle lang="ag" line="Who is galloping?"/><subtitle lang="dm" line="Who is galloping?"/><subtitle lang="vc" line="Who is galloping?"/><subtitle lang="bs" line="Who is galloping?"/><subtitle lang="ca" line="Who is galloping?"/><subtitle lang="bd" line="Who is galloping?"/><subtitle lang="bw" line="Who is galloping?"/><subtitle lang="fj" line="Who is galloping?"/><subtitle lang="gm" line="Who is galloping?"/><subtitle lang="gh" line="Who is galloping?"/><subtitle lang="gy" line="Who is galloping?"/><subtitle lang="ke" line="Who is galloping?"/><subtitle lang="mt" line="Who is galloping?"/><subtitle lang="mu" line="Who is galloping?"/><subtitle lang="na" line="Who is galloping?"/><subtitle lang="ng" line="Who is galloping?"/><subtitle lang="pk" line="Who is galloping?"/><subtitle lang="rw" line="Who is galloping?"/><subtitle lang="ws" line="Who is galloping?"/><subtitle lang="sl" line="Who is galloping?"/><subtitle lang="sg" line="Who is galloping?"/><subtitle lang="sb" line="Who is galloping?"/><subtitle lang="za" line="Who is galloping?"/><subtitle lang="tz" line="Who is galloping?"/><subtitle lang="to" line="Who is galloping?"/><subtitle lang="ug" line="Who is galloping?"/><subtitle lang="vu" line="Who is galloping?"/><subtitle lang="zm" line="Who is galloping?"/><subtitle lang="zw" line="Who is galloping?"/><subtitle lang="sco" line="Who is galloping?"/>
				<subtitle lang="ae" line="Who is galloping?"/>
			</subtitles>
    </line>
    <line words="&#x99AC;&#x304C;&#x8D70;&#x3063;&#x3066;&#x308B;&#x3000;&#x99AC;&#x304C;&#x8D70;&#x3063;&#x3066;&#x308B;" start="17927" length="8708">
      <subtitles>
        <subtitle lang="en" line="The horse is galloping, the horse is galloping."/>
      <subtitle lang="us" line="The horse is galloping, the horse is galloping."/><subtitle lang="au" line="The horse is galloping, the horse is galloping."/><subtitle lang="bz" line="The horse is galloping, the horse is galloping."/><subtitle lang="jm" line="The horse is galloping, the horse is galloping."/><subtitle lang="tt" line="The horse is galloping, the horse is galloping."/><subtitle lang="gy" line="The horse is galloping, the horse is galloping."/><subtitle lang="ag" line="The horse is galloping, the horse is galloping."/><subtitle lang="dm" line="The horse is galloping, the horse is galloping."/><subtitle lang="vc" line="The horse is galloping, the horse is galloping."/><subtitle lang="bs" line="The horse is galloping, the horse is galloping."/><subtitle lang="ca" line="The horse is galloping, the horse is galloping."/><subtitle lang="bd" line="The horse is galloping, the horse is galloping."/><subtitle lang="bw" line="The horse is galloping, the horse is galloping."/><subtitle lang="fj" line="The horse is galloping, the horse is galloping."/><subtitle lang="gm" line="The horse is galloping, the horse is galloping."/><subtitle lang="gh" line="The horse is galloping, the horse is galloping."/><subtitle lang="gy" line="The horse is galloping, the horse is galloping."/><subtitle lang="ke" line="The horse is galloping, the horse is galloping."/><subtitle lang="mt" line="The horse is galloping, the horse is galloping."/><subtitle lang="mu" line="The horse is galloping, the horse is galloping."/><subtitle lang="na" line="The horse is galloping, the horse is galloping."/><subtitle lang="ng" line="The horse is galloping, the horse is galloping."/><subtitle lang="pk" line="The horse is galloping, the horse is galloping."/><subtitle lang="rw" line="The horse is galloping, the horse is galloping."/><subtitle lang="ws" line="The horse is galloping, the horse is galloping."/><subtitle lang="sl" line="The horse is galloping, the horse is galloping."/><subtitle lang="sg" line="The horse is galloping, the horse is galloping."/><subtitle lang="sb" line="The horse is galloping, the horse is galloping."/><subtitle lang="za" line="The horse is galloping, the horse is galloping."/><subtitle lang="tz" line="The horse is galloping, the horse is galloping."/><subtitle lang="to" line="The horse is galloping, the horse is galloping."/><subtitle lang="ug" line="The horse is galloping, the horse is galloping."/><subtitle lang="vu" line="The horse is galloping, the horse is galloping."/><subtitle lang="zm" line="The horse is galloping, the horse is galloping."/><subtitle lang="zw" line="The horse is galloping, the horse is galloping."/><subtitle lang="sco" line="The horse is galloping, the horse is galloping."/>
				<subtitle lang="ae" line="The horse is galloping, the horse is galloping."/>
			</subtitles>
    </line>
    <line words="&#x3084;&#x3063;&#x305F;&#x3041;&#x3063;&#x3066;&#x99AC;&#x304C;&#x3055;&#x3051;&#x3093;&#x3067;&#x3044;&#x308B;&#x3088;&#x3002;" start="26891" length="8195">
      <subtitles>
        <subtitle lang="en" line="Yippie! The horse is shouting."/>
      <subtitle lang="us" line="Yippie! The horse is shouting."/><subtitle lang="au" line="Yippie! The horse is shouting."/><subtitle lang="bz" line="Yippie! The horse is shouting."/><subtitle lang="jm" line="Yippie! The horse is shouting."/><subtitle lang="tt" line="Yippie! The horse is shouting."/><subtitle lang="gy" line="Yippie! The horse is shouting."/><subtitle lang="ag" line="Yippie! The horse is shouting."/><subtitle lang="dm" line="Yippie! The horse is shouting."/><subtitle lang="vc" line="Yippie! The horse is shouting."/><subtitle lang="bs" line="Yippie! The horse is shouting."/><subtitle lang="ca" line="Yippie! The horse is shouting."/><subtitle lang="bd" line="Yippie! The horse is shouting."/><subtitle lang="bw" line="Yippie! The horse is shouting."/><subtitle lang="fj" line="Yippie! The horse is shouting."/><subtitle lang="gm" line="Yippie! The horse is shouting."/><subtitle lang="gh" line="Yippie! The horse is shouting."/><subtitle lang="gy" line="Yippie! The horse is shouting."/><subtitle lang="ke" line="Yippie! The horse is shouting."/><subtitle lang="mt" line="Yippie! The horse is shouting."/><subtitle lang="mu" line="Yippie! The horse is shouting."/><subtitle lang="na" line="Yippie! The horse is shouting."/><subtitle lang="ng" line="Yippie! The horse is shouting."/><subtitle lang="pk" line="Yippie! The horse is shouting."/><subtitle lang="rw" line="Yippie! The horse is shouting."/><subtitle lang="ws" line="Yippie! The horse is shouting."/><subtitle lang="sl" line="Yippie! The horse is shouting."/><subtitle lang="sg" line="Yippie! The horse is shouting."/><subtitle lang="sb" line="Yippie! The horse is shouting."/><subtitle lang="za" line="Yippie! The horse is shouting."/><subtitle lang="tz" line="Yippie! The horse is shouting."/><subtitle lang="to" line="Yippie! The horse is shouting."/><subtitle lang="ug" line="Yippie! The horse is shouting."/><subtitle lang="vu" line="Yippie! The horse is shouting."/><subtitle lang="zm" line="Yippie! The horse is shouting."/><subtitle lang="zw" line="Yippie! The horse is shouting."/><subtitle lang="sco" line="Yippie! The horse is shouting."/>
				<subtitle lang="ae" line="Yippie! The horse is shouting."/>
			</subtitles>
    </line>
    <line words="&#x3084;&#x3063;&#x305F;&#x3041;&#x3063;&#x3066;&#x99AC;&#x304C;&#x3055;&#x3051;&#x3093;&#x3067;&#x3044;&#x308B;&#x3088;&#x3002;" start="36367" length="7427">
      <subtitles>
        <subtitle lang="en" line="Yippie! The horse is shouting."/>
      <subtitle lang="us" line="Yippie! The horse is shouting."/><subtitle lang="au" line="Yippie! The horse is shouting."/><subtitle lang="bz" line="Yippie! The horse is shouting."/><subtitle lang="jm" line="Yippie! The horse is shouting."/><subtitle lang="tt" line="Yippie! The horse is shouting."/><subtitle lang="gy" line="Yippie! The horse is shouting."/><subtitle lang="ag" line="Yippie! The horse is shouting."/><subtitle lang="dm" line="Yippie! The horse is shouting."/><subtitle lang="vc" line="Yippie! The horse is shouting."/><subtitle lang="bs" line="Yippie! The horse is shouting."/><subtitle lang="ca" line="Yippie! The horse is shouting."/><subtitle lang="bd" line="Yippie! The horse is shouting."/><subtitle lang="bw" line="Yippie! The horse is shouting."/><subtitle lang="fj" line="Yippie! The horse is shouting."/><subtitle lang="gm" line="Yippie! The horse is shouting."/><subtitle lang="gh" line="Yippie! The horse is shouting."/><subtitle lang="gy" line="Yippie! The horse is shouting."/><subtitle lang="ke" line="Yippie! The horse is shouting."/><subtitle lang="mt" line="Yippie! The horse is shouting."/><subtitle lang="mu" line="Yippie! The horse is shouting."/><subtitle lang="na" line="Yippie! The horse is shouting."/><subtitle lang="ng" line="Yippie! The horse is shouting."/><subtitle lang="pk" line="Yippie! The horse is shouting."/><subtitle lang="rw" line="Yippie! The horse is shouting."/><subtitle lang="ws" line="Yippie! The horse is shouting."/><subtitle lang="sl" line="Yippie! The horse is shouting."/><subtitle lang="sg" line="Yippie! The horse is shouting."/><subtitle lang="sb" line="Yippie! The horse is shouting."/><subtitle lang="za" line="Yippie! The horse is shouting."/><subtitle lang="tz" line="Yippie! The horse is shouting."/><subtitle lang="to" line="Yippie! The horse is shouting."/><subtitle lang="ug" line="Yippie! The horse is shouting."/><subtitle lang="vu" line="Yippie! The horse is shouting."/><subtitle lang="zm" line="Yippie! The horse is shouting."/><subtitle lang="zw" line="Yippie! The horse is shouting."/><subtitle lang="sco" line="Yippie! The horse is shouting."/>
				<subtitle lang="ae" line="Yippie! The horse is shouting."/>
			</subtitles>
    </line>
    <line words="&#x3042;&#x308F;&#x3066;&#x3066;&#x308B;&#x306E;&#x306F;&#x8AB0;&#xFF1F;" start="49428" length="7683">
      <subtitles>
        <subtitle lang="en" line="Who is scampering by?"/>
      <subtitle lang="us" line="Who is scampering by?"/><subtitle lang="au" line="Who is scampering by?"/><subtitle lang="bz" line="Who is scampering by?"/><subtitle lang="jm" line="Who is scampering by?"/><subtitle lang="tt" line="Who is scampering by?"/><subtitle lang="gy" line="Who is scampering by?"/><subtitle lang="ag" line="Who is scampering by?"/><subtitle lang="dm" line="Who is scampering by?"/><subtitle lang="vc" line="Who is scampering by?"/><subtitle lang="bs" line="Who is scampering by?"/><subtitle lang="ca" line="Who is scampering by?"/><subtitle lang="bd" line="Who is scampering by?"/><subtitle lang="bw" line="Who is scampering by?"/><subtitle lang="fj" line="Who is scampering by?"/><subtitle lang="gm" line="Who is scampering by?"/><subtitle lang="gh" line="Who is scampering by?"/><subtitle lang="gy" line="Who is scampering by?"/><subtitle lang="ke" line="Who is scampering by?"/><subtitle lang="mt" line="Who is scampering by?"/><subtitle lang="mu" line="Who is scampering by?"/><subtitle lang="na" line="Who is scampering by?"/><subtitle lang="ng" line="Who is scampering by?"/><subtitle lang="pk" line="Who is scampering by?"/><subtitle lang="rw" line="Who is scampering by?"/><subtitle lang="ws" line="Who is scampering by?"/><subtitle lang="sl" line="Who is scampering by?"/><subtitle lang="sg" line="Who is scampering by?"/><subtitle lang="sb" line="Who is scampering by?"/><subtitle lang="za" line="Who is scampering by?"/><subtitle lang="tz" line="Who is scampering by?"/><subtitle lang="to" line="Who is scampering by?"/><subtitle lang="ug" line="Who is scampering by?"/><subtitle lang="vu" line="Who is scampering by?"/><subtitle lang="zm" line="Who is scampering by?"/><subtitle lang="zw" line="Who is scampering by?"/><subtitle lang="sco" line="Who is scampering by?"/>
				<subtitle lang="ae" line="Who is scampering by?"/>
			</subtitles>
    </line>
    <line words="&#x306D;&#x305A;&#x307F;&#x304C;&#x3042;&#x308F;&#x3066;&#x3066;&#x308B;&#x3000;&#x306D;&#x305A;&#x307F;&#x304C;&#x3042;&#x308F;&#x3066;&#x3066;&#x308B;" start="57111" length="9220">
      <subtitles>
        <subtitle lang="en" line="The mouse is scampering by, the mouse is scampering by."/>
      <subtitle lang="us" line="The mouse is scampering by, the mouse is scampering by."/><subtitle lang="au" line="The mouse is scampering by, the mouse is scampering by."/><subtitle lang="bz" line="The mouse is scampering by, the mouse is scampering by."/><subtitle lang="jm" line="The mouse is scampering by, the mouse is scampering by."/><subtitle lang="tt" line="The mouse is scampering by, the mouse is scampering by."/><subtitle lang="gy" line="The mouse is scampering by, the mouse is scampering by."/><subtitle lang="ag" line="The mouse is scampering by, the mouse is scampering by."/><subtitle lang="dm" line="The mouse is scampering by, the mouse is scampering by."/><subtitle lang="vc" line="The mouse is scampering by, the mouse is scampering by."/><subtitle lang="bs" line="The mouse is scampering by, the mouse is scampering by."/><subtitle lang="ca" line="The mouse is scampering by, the mouse is scampering by."/><subtitle lang="bd" line="The mouse is scampering by, the mouse is scampering by."/><subtitle lang="bw" line="The mouse is scampering by, the mouse is scampering by."/><subtitle lang="fj" line="The mouse is scampering by, the mouse is scampering by."/><subtitle lang="gm" line="The mouse is scampering by, the mouse is scampering by."/><subtitle lang="gh" line="The mouse is scampering by, the mouse is scampering by."/><subtitle lang="gy" line="The mouse is scampering by, the mouse is scampering by."/><subtitle lang="ke" line="The mouse is scampering by, the mouse is scampering by."/><subtitle lang="mt" line="The mouse is scampering by, the mouse is scampering by."/><subtitle lang="mu" line="The mouse is scampering by, the mouse is scampering by."/><subtitle lang="na" line="The mouse is scampering by, the mouse is scampering by."/><subtitle lang="ng" line="The mouse is scampering by, the mouse is scampering by."/><subtitle lang="pk" line="The mouse is scampering by, the mouse is scampering by."/><subtitle lang="rw" line="The mouse is scampering by, the mouse is scampering by."/><subtitle lang="ws" line="The mouse is scampering by, the mouse is scampering by."/><subtitle lang="sl" line="The mouse is scampering by, the mouse is scampering by."/><subtitle lang="sg" line="The mouse is scampering by, the mouse is scampering by."/><subtitle lang="sb" line="The mouse is scampering by, the mouse is scampering by."/><subtitle lang="za" line="The mouse is scampering by, the mouse is scampering by."/><subtitle lang="tz" line="The mouse is scampering by, the mouse is scampering by."/><subtitle lang="to" line="The mouse is scampering by, the mouse is scampering by."/><subtitle lang="ug" line="The mouse is scampering by, the mouse is scampering by."/><subtitle lang="vu" line="The mouse is scampering by, the mouse is scampering by."/><subtitle lang="zm" line="The mouse is scampering by, the mouse is scampering by."/><subtitle lang="zw" line="The mouse is scampering by, the mouse is scampering by."/><subtitle lang="sco" line="The mouse is scampering by, the mouse is scampering by."/>
				<subtitle lang="ae" line="The mouse is scampering by, the mouse is scampering by."/>
			</subtitles>
    </line>
    <line words="&#x3084;&#x3063;&#x305F;&#x3041;&#x3063;&#x3066;&#x306D;&#x305A;&#x307F;&#x304C;&#x3055;&#x3051;&#x3093;&#x3067;&#x3044;&#x308B;&#x3088;&#x3002;" start="66587" length="7939">
      <subtitles>
        <subtitle lang="en" line="Yippie! The mouse is shouting."/>
      <subtitle lang="us" line="Yippie! The mouse is shouting."/><subtitle lang="au" line="Yippie! The mouse is shouting."/><subtitle lang="bz" line="Yippie! The mouse is shouting."/><subtitle lang="jm" line="Yippie! The mouse is shouting."/><subtitle lang="tt" line="Yippie! The mouse is shouting."/><subtitle lang="gy" line="Yippie! The mouse is shouting."/><subtitle lang="ag" line="Yippie! The mouse is shouting."/><subtitle lang="dm" line="Yippie! The mouse is shouting."/><subtitle lang="vc" line="Yippie! The mouse is shouting."/><subtitle lang="bs" line="Yippie! The mouse is shouting."/><subtitle lang="ca" line="Yippie! The mouse is shouting."/><subtitle lang="bd" line="Yippie! The mouse is shouting."/><subtitle lang="bw" line="Yippie! The mouse is shouting."/><subtitle lang="fj" line="Yippie! The mouse is shouting."/><subtitle lang="gm" line="Yippie! The mouse is shouting."/><subtitle lang="gh" line="Yippie! The mouse is shouting."/><subtitle lang="gy" line="Yippie! The mouse is shouting."/><subtitle lang="ke" line="Yippie! The mouse is shouting."/><subtitle lang="mt" line="Yippie! The mouse is shouting."/><subtitle lang="mu" line="Yippie! The mouse is shouting."/><subtitle lang="na" line="Yippie! The mouse is shouting."/><subtitle lang="ng" line="Yippie! The mouse is shouting."/><subtitle lang="pk" line="Yippie! The mouse is shouting."/><subtitle lang="rw" line="Yippie! The mouse is shouting."/><subtitle lang="ws" line="Yippie! The mouse is shouting."/><subtitle lang="sl" line="Yippie! The mouse is shouting."/><subtitle lang="sg" line="Yippie! The mouse is shouting."/><subtitle lang="sb" line="Yippie! The mouse is shouting."/><subtitle lang="za" line="Yippie! The mouse is shouting."/><subtitle lang="tz" line="Yippie! The mouse is shouting."/><subtitle lang="to" line="Yippie! The mouse is shouting."/><subtitle lang="ug" line="Yippie! The mouse is shouting."/><subtitle lang="vu" line="Yippie! The mouse is shouting."/><subtitle lang="zm" line="Yippie! The mouse is shouting."/><subtitle lang="zw" line="Yippie! The mouse is shouting."/><subtitle lang="sco" line="Yippie! The mouse is shouting."/>
				<subtitle lang="ae" line="Yippie! The mouse is shouting."/>
			</subtitles>
    </line>
    <line words="&#x3084;&#x3063;&#x305F;&#x3041;&#x3063;&#x3066;&#x306D;&#x305A;&#x307F;&#x304C;&#x3055;&#x3051;&#x3093;&#x3067;&#x3044;&#x308B;&#x3088;&#x3002;" start="74782" length="8964">
      <subtitles>
        <subtitle lang="en" line="Yippie! The mouse is shouting."/>
      <subtitle lang="us" line="Yippie! The mouse is shouting."/><subtitle lang="au" line="Yippie! The mouse is shouting."/><subtitle lang="bz" line="Yippie! The mouse is shouting."/><subtitle lang="jm" line="Yippie! The mouse is shouting."/><subtitle lang="tt" line="Yippie! The mouse is shouting."/><subtitle lang="gy" line="Yippie! The mouse is shouting."/><subtitle lang="ag" line="Yippie! The mouse is shouting."/><subtitle lang="dm" line="Yippie! The mouse is shouting."/><subtitle lang="vc" line="Yippie! The mouse is shouting."/><subtitle lang="bs" line="Yippie! The mouse is shouting."/><subtitle lang="ca" line="Yippie! The mouse is shouting."/><subtitle lang="bd" line="Yippie! The mouse is shouting."/><subtitle lang="bw" line="Yippie! The mouse is shouting."/><subtitle lang="fj" line="Yippie! The mouse is shouting."/><subtitle lang="gm" line="Yippie! The mouse is shouting."/><subtitle lang="gh" line="Yippie! The mouse is shouting."/><subtitle lang="gy" line="Yippie! The mouse is shouting."/><subtitle lang="ke" line="Yippie! The mouse is shouting."/><subtitle lang="mt" line="Yippie! The mouse is shouting."/><subtitle lang="mu" line="Yippie! The mouse is shouting."/><subtitle lang="na" line="Yippie! The mouse is shouting."/><subtitle lang="ng" line="Yippie! The mouse is shouting."/><subtitle lang="pk" line="Yippie! The mouse is shouting."/><subtitle lang="rw" line="Yippie! The mouse is shouting."/><subtitle lang="ws" line="Yippie! The mouse is shouting."/><subtitle lang="sl" line="Yippie! The mouse is shouting."/><subtitle lang="sg" line="Yippie! The mouse is shouting."/><subtitle lang="sb" line="Yippie! The mouse is shouting."/><subtitle lang="za" line="Yippie! The mouse is shouting."/><subtitle lang="tz" line="Yippie! The mouse is shouting."/><subtitle lang="to" line="Yippie! The mouse is shouting."/><subtitle lang="ug" line="Yippie! The mouse is shouting."/><subtitle lang="vu" line="Yippie! The mouse is shouting."/><subtitle lang="zm" line="Yippie! The mouse is shouting."/><subtitle lang="zw" line="Yippie! The mouse is shouting."/><subtitle lang="sco" line="Yippie! The mouse is shouting."/>
				<subtitle lang="ae" line="Yippie! The mouse is shouting."/>
			</subtitles>
    </line>
    <line words="&#x306F;&#x306D;&#x3066;&#x3044;&#x308B;&#x306E;&#x306F;&#x8AB0;&#xFF1F;&#9;" start="88100" length="8452">
      <subtitles>
        <subtitle lang="en" line="Who is hopping by?"/>
      <subtitle lang="us" line="Who is hopping by?"/><subtitle lang="au" line="Who is hopping by?"/><subtitle lang="bz" line="Who is hopping by?"/><subtitle lang="jm" line="Who is hopping by?"/><subtitle lang="tt" line="Who is hopping by?"/><subtitle lang="gy" line="Who is hopping by?"/><subtitle lang="ag" line="Who is hopping by?"/><subtitle lang="dm" line="Who is hopping by?"/><subtitle lang="vc" line="Who is hopping by?"/><subtitle lang="bs" line="Who is hopping by?"/><subtitle lang="ca" line="Who is hopping by?"/><subtitle lang="bd" line="Who is hopping by?"/><subtitle lang="bw" line="Who is hopping by?"/><subtitle lang="fj" line="Who is hopping by?"/><subtitle lang="gm" line="Who is hopping by?"/><subtitle lang="gh" line="Who is hopping by?"/><subtitle lang="gy" line="Who is hopping by?"/><subtitle lang="ke" line="Who is hopping by?"/><subtitle lang="mt" line="Who is hopping by?"/><subtitle lang="mu" line="Who is hopping by?"/><subtitle lang="na" line="Who is hopping by?"/><subtitle lang="ng" line="Who is hopping by?"/><subtitle lang="pk" line="Who is hopping by?"/><subtitle lang="rw" line="Who is hopping by?"/><subtitle lang="ws" line="Who is hopping by?"/><subtitle lang="sl" line="Who is hopping by?"/><subtitle lang="sg" line="Who is hopping by?"/><subtitle lang="sb" line="Who is hopping by?"/><subtitle lang="za" line="Who is hopping by?"/><subtitle lang="tz" line="Who is hopping by?"/><subtitle lang="to" line="Who is hopping by?"/><subtitle lang="ug" line="Who is hopping by?"/><subtitle lang="vu" line="Who is hopping by?"/><subtitle lang="zm" line="Who is hopping by?"/><subtitle lang="zw" line="Who is hopping by?"/><subtitle lang="sco" line="Who is hopping by?"/>
				<subtitle lang="ae" line="Who is hopping by?"/>
			</subtitles>
    </line>
    <line words="&#x3046;&#x3055;&#x304E;&#x304C;&#x306F;&#x306D;&#x3066;&#x3044;&#x308B;&#x3000;&#x3046;&#x3055;&#x304E;&#x304C;&#x306F;&#x306D;&#x3066;&#x308B;" start="96808" length="9219">
      <subtitles>
        <subtitle lang="en" line="The rabbit is hopping by, the rabbit is hopping by."/>
      <subtitle lang="us" line="The rabbit is hopping by, the rabbit is hopping by."/><subtitle lang="au" line="The rabbit is hopping by, the rabbit is hopping by."/><subtitle lang="bz" line="The rabbit is hopping by, the rabbit is hopping by."/><subtitle lang="jm" line="The rabbit is hopping by, the rabbit is hopping by."/><subtitle lang="tt" line="The rabbit is hopping by, the rabbit is hopping by."/><subtitle lang="gy" line="The rabbit is hopping by, the rabbit is hopping by."/><subtitle lang="ag" line="The rabbit is hopping by, the rabbit is hopping by."/><subtitle lang="dm" line="The rabbit is hopping by, the rabbit is hopping by."/><subtitle lang="vc" line="The rabbit is hopping by, the rabbit is hopping by."/><subtitle lang="bs" line="The rabbit is hopping by, the rabbit is hopping by."/><subtitle lang="ca" line="The rabbit is hopping by, the rabbit is hopping by."/><subtitle lang="bd" line="The rabbit is hopping by, the rabbit is hopping by."/><subtitle lang="bw" line="The rabbit is hopping by, the rabbit is hopping by."/><subtitle lang="fj" line="The rabbit is hopping by, the rabbit is hopping by."/><subtitle lang="gm" line="The rabbit is hopping by, the rabbit is hopping by."/><subtitle lang="gh" line="The rabbit is hopping by, the rabbit is hopping by."/><subtitle lang="gy" line="The rabbit is hopping by, the rabbit is hopping by."/><subtitle lang="ke" line="The rabbit is hopping by, the rabbit is hopping by."/><subtitle lang="mt" line="The rabbit is hopping by, the rabbit is hopping by."/><subtitle lang="mu" line="The rabbit is hopping by, the rabbit is hopping by."/><subtitle lang="na" line="The rabbit is hopping by, the rabbit is hopping by."/><subtitle lang="ng" line="The rabbit is hopping by, the rabbit is hopping by."/><subtitle lang="pk" line="The rabbit is hopping by, the rabbit is hopping by."/><subtitle lang="rw" line="The rabbit is hopping by, the rabbit is hopping by."/><subtitle lang="ws" line="The rabbit is hopping by, the rabbit is hopping by."/><subtitle lang="sl" line="The rabbit is hopping by, the rabbit is hopping by."/><subtitle lang="sg" line="The rabbit is hopping by, the rabbit is hopping by."/><subtitle lang="sb" line="The rabbit is hopping by, the rabbit is hopping by."/><subtitle lang="za" line="The rabbit is hopping by, the rabbit is hopping by."/><subtitle lang="tz" line="The rabbit is hopping by, the rabbit is hopping by."/><subtitle lang="to" line="The rabbit is hopping by, the rabbit is hopping by."/><subtitle lang="ug" line="The rabbit is hopping by, the rabbit is hopping by."/><subtitle lang="vu" line="The rabbit is hopping by, the rabbit is hopping by."/><subtitle lang="zm" line="The rabbit is hopping by, the rabbit is hopping by."/><subtitle lang="zw" line="The rabbit is hopping by, the rabbit is hopping by."/><subtitle lang="sco" line="The rabbit is hopping by, the rabbit is hopping by."/>
				<subtitle lang="ae" line="The rabbit is hopping by, the rabbit is hopping by."/>
			</subtitles>
    </line>
    <line words="&#x3084;&#x3063;&#x305F;&#x3041;&#x3063;&#x3066;&#x3046;&#x3055;&#x304E;&#x304C;&#x3055;&#x3051;&#x3093;&#x3067;&#x3044;&#x308B;&#x3088;&#x3002;" start="106027" length="7940">
      <subtitles>
        <subtitle lang="en" line="Yippie! The rabbit is shouting."/>
      <subtitle lang="us" line="Yippie! The rabbit is shouting."/><subtitle lang="au" line="Yippie! The rabbit is shouting."/><subtitle lang="bz" line="Yippie! The rabbit is shouting."/><subtitle lang="jm" line="Yippie! The rabbit is shouting."/><subtitle lang="tt" line="Yippie! The rabbit is shouting."/><subtitle lang="gy" line="Yippie! The rabbit is shouting."/><subtitle lang="ag" line="Yippie! The rabbit is shouting."/><subtitle lang="dm" line="Yippie! The rabbit is shouting."/><subtitle lang="vc" line="Yippie! The rabbit is shouting."/><subtitle lang="bs" line="Yippie! The rabbit is shouting."/><subtitle lang="ca" line="Yippie! The rabbit is shouting."/><subtitle lang="bd" line="Yippie! The rabbit is shouting."/><subtitle lang="bw" line="Yippie! The rabbit is shouting."/><subtitle lang="fj" line="Yippie! The rabbit is shouting."/><subtitle lang="gm" line="Yippie! The rabbit is shouting."/><subtitle lang="gh" line="Yippie! The rabbit is shouting."/><subtitle lang="gy" line="Yippie! The rabbit is shouting."/><subtitle lang="ke" line="Yippie! The rabbit is shouting."/><subtitle lang="mt" line="Yippie! The rabbit is shouting."/><subtitle lang="mu" line="Yippie! The rabbit is shouting."/><subtitle lang="na" line="Yippie! The rabbit is shouting."/><subtitle lang="ng" line="Yippie! The rabbit is shouting."/><subtitle lang="pk" line="Yippie! The rabbit is shouting."/><subtitle lang="rw" line="Yippie! The rabbit is shouting."/><subtitle lang="ws" line="Yippie! The rabbit is shouting."/><subtitle lang="sl" line="Yippie! The rabbit is shouting."/><subtitle lang="sg" line="Yippie! The rabbit is shouting."/><subtitle lang="sb" line="Yippie! The rabbit is shouting."/><subtitle lang="za" line="Yippie! The rabbit is shouting."/><subtitle lang="tz" line="Yippie! The rabbit is shouting."/><subtitle lang="to" line="Yippie! The rabbit is shouting."/><subtitle lang="ug" line="Yippie! The rabbit is shouting."/><subtitle lang="vu" line="Yippie! The rabbit is shouting."/><subtitle lang="zm" line="Yippie! The rabbit is shouting."/><subtitle lang="zw" line="Yippie! The rabbit is shouting."/><subtitle lang="sco" line="Yippie! The rabbit is shouting."/>
				<subtitle lang="ae" line="Yippie! The rabbit is shouting."/>
			</subtitles>
    </line>
    <line words="&#x3084;&#x3063;&#x305F;&#x3041;&#x3063;&#x3066;&#x3046;&#x3055;&#x304E;&#x304C;&#x3055;&#x3051;&#x3093;&#x3067;&#x3044;&#x308B;&#x3088;&#x3002;" start="113967" length="9476">
      <subtitles>
        <subtitle lang="en" line="Yippie! The rabbit is shouting."/>
      <subtitle lang="us" line="Yippie! The rabbit is shouting."/><subtitle lang="au" line="Yippie! The rabbit is shouting."/><subtitle lang="bz" line="Yippie! The rabbit is shouting."/><subtitle lang="jm" line="Yippie! The rabbit is shouting."/><subtitle lang="tt" line="Yippie! The rabbit is shouting."/><subtitle lang="gy" line="Yippie! The rabbit is shouting."/><subtitle lang="ag" line="Yippie! The rabbit is shouting."/><subtitle lang="dm" line="Yippie! The rabbit is shouting."/><subtitle lang="vc" line="Yippie! The rabbit is shouting."/><subtitle lang="bs" line="Yippie! The rabbit is shouting."/><subtitle lang="ca" line="Yippie! The rabbit is shouting."/><subtitle lang="bd" line="Yippie! The rabbit is shouting."/><subtitle lang="bw" line="Yippie! The rabbit is shouting."/><subtitle lang="fj" line="Yippie! The rabbit is shouting."/><subtitle lang="gm" line="Yippie! The rabbit is shouting."/><subtitle lang="gh" line="Yippie! The rabbit is shouting."/><subtitle lang="gy" line="Yippie! The rabbit is shouting."/><subtitle lang="ke" line="Yippie! The rabbit is shouting."/><subtitle lang="mt" line="Yippie! The rabbit is shouting."/><subtitle lang="mu" line="Yippie! The rabbit is shouting."/><subtitle lang="na" line="Yippie! The rabbit is shouting."/><subtitle lang="ng" line="Yippie! The rabbit is shouting."/><subtitle lang="pk" line="Yippie! The rabbit is shouting."/><subtitle lang="rw" line="Yippie! The rabbit is shouting."/><subtitle lang="ws" line="Yippie! The rabbit is shouting."/><subtitle lang="sl" line="Yippie! The rabbit is shouting."/><subtitle lang="sg" line="Yippie! The rabbit is shouting."/><subtitle lang="sb" line="Yippie! The rabbit is shouting."/><subtitle lang="za" line="Yippie! The rabbit is shouting."/><subtitle lang="tz" line="Yippie! The rabbit is shouting."/><subtitle lang="to" line="Yippie! The rabbit is shouting."/><subtitle lang="ug" line="Yippie! The rabbit is shouting."/><subtitle lang="vu" line="Yippie! The rabbit is shouting."/><subtitle lang="zm" line="Yippie! The rabbit is shouting."/><subtitle lang="zw" line="Yippie! The rabbit is shouting."/><subtitle lang="sco" line="Yippie! The rabbit is shouting."/>
				<subtitle lang="ae" line="Yippie! The rabbit is shouting."/>
			</subtitles>
    </line>
    <line words="&#x8D70;&#x3063;&#x3066;&#x308B;&#x306E;&#x306F;&#x8AB0;&#xFF1F;" start="127284" length="8196">
      <subtitles>
        <subtitle lang="en" line="Who is running by?"/>
      <subtitle lang="us" line="Who is running by?"/><subtitle lang="au" line="Who is running by?"/><subtitle lang="bz" line="Who is running by?"/><subtitle lang="jm" line="Who is running by?"/><subtitle lang="tt" line="Who is running by?"/><subtitle lang="gy" line="Who is running by?"/><subtitle lang="ag" line="Who is running by?"/><subtitle lang="dm" line="Who is running by?"/><subtitle lang="vc" line="Who is running by?"/><subtitle lang="bs" line="Who is running by?"/><subtitle lang="ca" line="Who is running by?"/><subtitle lang="bd" line="Who is running by?"/><subtitle lang="bw" line="Who is running by?"/><subtitle lang="fj" line="Who is running by?"/><subtitle lang="gm" line="Who is running by?"/><subtitle lang="gh" line="Who is running by?"/><subtitle lang="gy" line="Who is running by?"/><subtitle lang="ke" line="Who is running by?"/><subtitle lang="mt" line="Who is running by?"/><subtitle lang="mu" line="Who is running by?"/><subtitle lang="na" line="Who is running by?"/><subtitle lang="ng" line="Who is running by?"/><subtitle lang="pk" line="Who is running by?"/><subtitle lang="rw" line="Who is running by?"/><subtitle lang="ws" line="Who is running by?"/><subtitle lang="sl" line="Who is running by?"/><subtitle lang="sg" line="Who is running by?"/><subtitle lang="sb" line="Who is running by?"/><subtitle lang="za" line="Who is running by?"/><subtitle lang="tz" line="Who is running by?"/><subtitle lang="to" line="Who is running by?"/><subtitle lang="ug" line="Who is running by?"/><subtitle lang="vu" line="Who is running by?"/><subtitle lang="zm" line="Who is running by?"/><subtitle lang="zw" line="Who is running by?"/><subtitle lang="sco" line="Who is running by?"/>
				<subtitle lang="ae" line="Who is running by?"/>
			</subtitles>
    </line>
    <line words="&#x3072;&#x3064;&#x3058;&#x304C;&#x8D70;&#x3063;&#x3066;&#x308B;&#x3000;&#x3072;&#x3064;&#x3058;&#x304C;&#x8D70;&#x3063;&#x3066;&#x308B;" start="135992" length="8451">
      <subtitles>
        <subtitle lang="en" line="The sheep is running by, the sheep is running by."/>
      <subtitle lang="us" line="The sheep is running by, the sheep is running by."/><subtitle lang="au" line="The sheep is running by, the sheep is running by."/><subtitle lang="bz" line="The sheep is running by, the sheep is running by."/><subtitle lang="jm" line="The sheep is running by, the sheep is running by."/><subtitle lang="tt" line="The sheep is running by, the sheep is running by."/><subtitle lang="gy" line="The sheep is running by, the sheep is running by."/><subtitle lang="ag" line="The sheep is running by, the sheep is running by."/><subtitle lang="dm" line="The sheep is running by, the sheep is running by."/><subtitle lang="vc" line="The sheep is running by, the sheep is running by."/><subtitle lang="bs" line="The sheep is running by, the sheep is running by."/><subtitle lang="ca" line="The sheep is running by, the sheep is running by."/><subtitle lang="bd" line="The sheep is running by, the sheep is running by."/><subtitle lang="bw" line="The sheep is running by, the sheep is running by."/><subtitle lang="fj" line="The sheep is running by, the sheep is running by."/><subtitle lang="gm" line="The sheep is running by, the sheep is running by."/><subtitle lang="gh" line="The sheep is running by, the sheep is running by."/><subtitle lang="gy" line="The sheep is running by, the sheep is running by."/><subtitle lang="ke" line="The sheep is running by, the sheep is running by."/><subtitle lang="mt" line="The sheep is running by, the sheep is running by."/><subtitle lang="mu" line="The sheep is running by, the sheep is running by."/><subtitle lang="na" line="The sheep is running by, the sheep is running by."/><subtitle lang="ng" line="The sheep is running by, the sheep is running by."/><subtitle lang="pk" line="The sheep is running by, the sheep is running by."/><subtitle lang="rw" line="The sheep is running by, the sheep is running by."/><subtitle lang="ws" line="The sheep is running by, the sheep is running by."/><subtitle lang="sl" line="The sheep is running by, the sheep is running by."/><subtitle lang="sg" line="The sheep is running by, the sheep is running by."/><subtitle lang="sb" line="The sheep is running by, the sheep is running by."/><subtitle lang="za" line="The sheep is running by, the sheep is running by."/><subtitle lang="tz" line="The sheep is running by, the sheep is running by."/><subtitle lang="to" line="The sheep is running by, the sheep is running by."/><subtitle lang="ug" line="The sheep is running by, the sheep is running by."/><subtitle lang="vu" line="The sheep is running by, the sheep is running by."/><subtitle lang="zm" line="The sheep is running by, the sheep is running by."/><subtitle lang="zw" line="The sheep is running by, the sheep is running by."/><subtitle lang="sco" line="The sheep is running by, the sheep is running by."/>
				<subtitle lang="ae" line="The sheep is running by, the sheep is running by."/>
			</subtitles>
    </line>
    <line words="&#x3084;&#x3063;&#x305F;&#x3041;&#x3063;&#x3066;&#x3072;&#x3064;&#x3058;&#x304C;&#x3055;&#x3051;&#x3093;&#x3067;&#x3044;&#x308B;&#x3088;&#x3002;" start="144699" length="8196">
      <subtitles>
        <subtitle lang="en" line="Yippie! The sheep is shouting."/>
      <subtitle lang="us" line="Yippie! The sheep is shouting."/><subtitle lang="au" line="Yippie! The sheep is shouting."/><subtitle lang="bz" line="Yippie! The sheep is shouting."/><subtitle lang="jm" line="Yippie! The sheep is shouting."/><subtitle lang="tt" line="Yippie! The sheep is shouting."/><subtitle lang="gy" line="Yippie! The sheep is shouting."/><subtitle lang="ag" line="Yippie! The sheep is shouting."/><subtitle lang="dm" line="Yippie! The sheep is shouting."/><subtitle lang="vc" line="Yippie! The sheep is shouting."/><subtitle lang="bs" line="Yippie! The sheep is shouting."/><subtitle lang="ca" line="Yippie! The sheep is shouting."/><subtitle lang="bd" line="Yippie! The sheep is shouting."/><subtitle lang="bw" line="Yippie! The sheep is shouting."/><subtitle lang="fj" line="Yippie! The sheep is shouting."/><subtitle lang="gm" line="Yippie! The sheep is shouting."/><subtitle lang="gh" line="Yippie! The sheep is shouting."/><subtitle lang="gy" line="Yippie! The sheep is shouting."/><subtitle lang="ke" line="Yippie! The sheep is shouting."/><subtitle lang="mt" line="Yippie! The sheep is shouting."/><subtitle lang="mu" line="Yippie! The sheep is shouting."/><subtitle lang="na" line="Yippie! The sheep is shouting."/><subtitle lang="ng" line="Yippie! The sheep is shouting."/><subtitle lang="pk" line="Yippie! The sheep is shouting."/><subtitle lang="rw" line="Yippie! The sheep is shouting."/><subtitle lang="ws" line="Yippie! The sheep is shouting."/><subtitle lang="sl" line="Yippie! The sheep is shouting."/><subtitle lang="sg" line="Yippie! The sheep is shouting."/><subtitle lang="sb" line="Yippie! The sheep is shouting."/><subtitle lang="za" line="Yippie! The sheep is shouting."/><subtitle lang="tz" line="Yippie! The sheep is shouting."/><subtitle lang="to" line="Yippie! The sheep is shouting."/><subtitle lang="ug" line="Yippie! The sheep is shouting."/><subtitle lang="vu" line="Yippie! The sheep is shouting."/><subtitle lang="zm" line="Yippie! The sheep is shouting."/><subtitle lang="zw" line="Yippie! The sheep is shouting."/><subtitle lang="sco" line="Yippie! The sheep is shouting."/>
				<subtitle lang="ae" line="Yippie! The sheep is shouting."/>
			</subtitles>
    </line>
    <line words="&#x3084;&#x3063;&#x305F;&#x3041;&#x3063;&#x3066;&#x3072;&#x3064;&#x3058;&#x304C;&#x3055;&#x3051;&#x3093;&#x3067;&#x3044;&#x308B;&#x3088;&#x3002;" start="153407" length="8195">
      <subtitles>
        <subtitle lang="en" line="Yippie! The sheep is shouting."/>
      <subtitle lang="us" line="Yippie! The sheep is shouting."/><subtitle lang="au" line="Yippie! The sheep is shouting."/><subtitle lang="bz" line="Yippie! The sheep is shouting."/><subtitle lang="jm" line="Yippie! The sheep is shouting."/><subtitle lang="tt" line="Yippie! The sheep is shouting."/><subtitle lang="gy" line="Yippie! The sheep is shouting."/><subtitle lang="ag" line="Yippie! The sheep is shouting."/><subtitle lang="dm" line="Yippie! The sheep is shouting."/><subtitle lang="vc" line="Yippie! The sheep is shouting."/><subtitle lang="bs" line="Yippie! The sheep is shouting."/><subtitle lang="ca" line="Yippie! The sheep is shouting."/><subtitle lang="bd" line="Yippie! The sheep is shouting."/><subtitle lang="bw" line="Yippie! The sheep is shouting."/><subtitle lang="fj" line="Yippie! The sheep is shouting."/><subtitle lang="gm" line="Yippie! The sheep is shouting."/><subtitle lang="gh" line="Yippie! The sheep is shouting."/><subtitle lang="gy" line="Yippie! The sheep is shouting."/><subtitle lang="ke" line="Yippie! The sheep is shouting."/><subtitle lang="mt" line="Yippie! The sheep is shouting."/><subtitle lang="mu" line="Yippie! The sheep is shouting."/><subtitle lang="na" line="Yippie! The sheep is shouting."/><subtitle lang="ng" line="Yippie! The sheep is shouting."/><subtitle lang="pk" line="Yippie! The sheep is shouting."/><subtitle lang="rw" line="Yippie! The sheep is shouting."/><subtitle lang="ws" line="Yippie! The sheep is shouting."/><subtitle lang="sl" line="Yippie! The sheep is shouting."/><subtitle lang="sg" line="Yippie! The sheep is shouting."/><subtitle lang="sb" line="Yippie! The sheep is shouting."/><subtitle lang="za" line="Yippie! The sheep is shouting."/><subtitle lang="tz" line="Yippie! The sheep is shouting."/><subtitle lang="to" line="Yippie! The sheep is shouting."/><subtitle lang="ug" line="Yippie! The sheep is shouting."/><subtitle lang="vu" line="Yippie! The sheep is shouting."/><subtitle lang="zm" line="Yippie! The sheep is shouting."/><subtitle lang="zw" line="Yippie! The sheep is shouting."/><subtitle lang="sco" line="Yippie! The sheep is shouting."/>
				<subtitle lang="ae" line="Yippie! The sheep is shouting."/>
			</subtitles>
    </line>
    <line words="&#x8E0A;&#x3063;&#x3066;&#x308B;&#x306E;&#x306F;&#x8AB0;&#xFF1F;&#9;" start="166981" length="7427">
      <subtitles>
        <subtitle lang="en" line="Who is dancing?"/>
      <subtitle lang="us" line="Who is dancing?"/><subtitle lang="au" line="Who is dancing?"/><subtitle lang="bz" line="Who is dancing?"/><subtitle lang="jm" line="Who is dancing?"/><subtitle lang="tt" line="Who is dancing?"/><subtitle lang="gy" line="Who is dancing?"/><subtitle lang="ag" line="Who is dancing?"/><subtitle lang="dm" line="Who is dancing?"/><subtitle lang="vc" line="Who is dancing?"/><subtitle lang="bs" line="Who is dancing?"/><subtitle lang="ca" line="Who is dancing?"/><subtitle lang="bd" line="Who is dancing?"/><subtitle lang="bw" line="Who is dancing?"/><subtitle lang="fj" line="Who is dancing?"/><subtitle lang="gm" line="Who is dancing?"/><subtitle lang="gh" line="Who is dancing?"/><subtitle lang="gy" line="Who is dancing?"/><subtitle lang="ke" line="Who is dancing?"/><subtitle lang="mt" line="Who is dancing?"/><subtitle lang="mu" line="Who is dancing?"/><subtitle lang="na" line="Who is dancing?"/><subtitle lang="ng" line="Who is dancing?"/><subtitle lang="pk" line="Who is dancing?"/><subtitle lang="rw" line="Who is dancing?"/><subtitle lang="ws" line="Who is dancing?"/><subtitle lang="sl" line="Who is dancing?"/><subtitle lang="sg" line="Who is dancing?"/><subtitle lang="sb" line="Who is dancing?"/><subtitle lang="za" line="Who is dancing?"/><subtitle lang="tz" line="Who is dancing?"/><subtitle lang="to" line="Who is dancing?"/><subtitle lang="ug" line="Who is dancing?"/><subtitle lang="vu" line="Who is dancing?"/><subtitle lang="zm" line="Who is dancing?"/><subtitle lang="zw" line="Who is dancing?"/><subtitle lang="sco" line="Who is dancing?"/>
				<subtitle lang="ae" line="Who is dancing?"/>
			</subtitles>
    </line>
    <line words="&#x725B;&#x304C;&#x8E0A;&#x3063;&#x3066;&#x3044;&#x308B;&#x3000;&#x725B;&#x304C;&#x8E0A;&#x3063;&#x3066;&#x308B;&#9;" start="175432" length="8452">
      <subtitles>
        <subtitle lang="en" line="The cow is dancing, the cow is dancing."/>
      <subtitle lang="us" line="The cow is dancing, the cow is dancing."/><subtitle lang="au" line="The cow is dancing, the cow is dancing."/><subtitle lang="bz" line="The cow is dancing, the cow is dancing."/><subtitle lang="jm" line="The cow is dancing, the cow is dancing."/><subtitle lang="tt" line="The cow is dancing, the cow is dancing."/><subtitle lang="gy" line="The cow is dancing, the cow is dancing."/><subtitle lang="ag" line="The cow is dancing, the cow is dancing."/><subtitle lang="dm" line="The cow is dancing, the cow is dancing."/><subtitle lang="vc" line="The cow is dancing, the cow is dancing."/><subtitle lang="bs" line="The cow is dancing, the cow is dancing."/><subtitle lang="ca" line="The cow is dancing, the cow is dancing."/><subtitle lang="bd" line="The cow is dancing, the cow is dancing."/><subtitle lang="bw" line="The cow is dancing, the cow is dancing."/><subtitle lang="fj" line="The cow is dancing, the cow is dancing."/><subtitle lang="gm" line="The cow is dancing, the cow is dancing."/><subtitle lang="gh" line="The cow is dancing, the cow is dancing."/><subtitle lang="gy" line="The cow is dancing, the cow is dancing."/><subtitle lang="ke" line="The cow is dancing, the cow is dancing."/><subtitle lang="mt" line="The cow is dancing, the cow is dancing."/><subtitle lang="mu" line="The cow is dancing, the cow is dancing."/><subtitle lang="na" line="The cow is dancing, the cow is dancing."/><subtitle lang="ng" line="The cow is dancing, the cow is dancing."/><subtitle lang="pk" line="The cow is dancing, the cow is dancing."/><subtitle lang="rw" line="The cow is dancing, the cow is dancing."/><subtitle lang="ws" line="The cow is dancing, the cow is dancing."/><subtitle lang="sl" line="The cow is dancing, the cow is dancing."/><subtitle lang="sg" line="The cow is dancing, the cow is dancing."/><subtitle lang="sb" line="The cow is dancing, the cow is dancing."/><subtitle lang="za" line="The cow is dancing, the cow is dancing."/><subtitle lang="tz" line="The cow is dancing, the cow is dancing."/><subtitle lang="to" line="The cow is dancing, the cow is dancing."/><subtitle lang="ug" line="The cow is dancing, the cow is dancing."/><subtitle lang="vu" line="The cow is dancing, the cow is dancing."/><subtitle lang="zm" line="The cow is dancing, the cow is dancing."/><subtitle lang="zw" line="The cow is dancing, the cow is dancing."/><subtitle lang="sco" line="The cow is dancing, the cow is dancing."/>
				<subtitle lang="ae" line="The cow is dancing, the cow is dancing."/>
			</subtitles>
    </line>
    <line words="&#x3084;&#x3063;&#x305F;&#x3041;&#x3063;&#x3066;&#x3072;&#x3064;&#x3058;&#x304C;&#x3055;&#x3051;&#x3093;&#x3067;&#x3044;&#x308B;&#x3088;&#x3002;" start="184652" length="7683">
      <subtitles>
        <subtitle lang="en" line="Yippie! The cow is shouting."/>
      <subtitle lang="us" line="Yippie! The cow is shouting."/><subtitle lang="au" line="Yippie! The cow is shouting."/><subtitle lang="bz" line="Yippie! The cow is shouting."/><subtitle lang="jm" line="Yippie! The cow is shouting."/><subtitle lang="tt" line="Yippie! The cow is shouting."/><subtitle lang="gy" line="Yippie! The cow is shouting."/><subtitle lang="ag" line="Yippie! The cow is shouting."/><subtitle lang="dm" line="Yippie! The cow is shouting."/><subtitle lang="vc" line="Yippie! The cow is shouting."/><subtitle lang="bs" line="Yippie! The cow is shouting."/><subtitle lang="ca" line="Yippie! The cow is shouting."/><subtitle lang="bd" line="Yippie! The cow is shouting."/><subtitle lang="bw" line="Yippie! The cow is shouting."/><subtitle lang="fj" line="Yippie! The cow is shouting."/><subtitle lang="gm" line="Yippie! The cow is shouting."/><subtitle lang="gh" line="Yippie! The cow is shouting."/><subtitle lang="gy" line="Yippie! The cow is shouting."/><subtitle lang="ke" line="Yippie! The cow is shouting."/><subtitle lang="mt" line="Yippie! The cow is shouting."/><subtitle lang="mu" line="Yippie! The cow is shouting."/><subtitle lang="na" line="Yippie! The cow is shouting."/><subtitle lang="ng" line="Yippie! The cow is shouting."/><subtitle lang="pk" line="Yippie! The cow is shouting."/><subtitle lang="rw" line="Yippie! The cow is shouting."/><subtitle lang="ws" line="Yippie! The cow is shouting."/><subtitle lang="sl" line="Yippie! The cow is shouting."/><subtitle lang="sg" line="Yippie! The cow is shouting."/><subtitle lang="sb" line="Yippie! The cow is shouting."/><subtitle lang="za" line="Yippie! The cow is shouting."/><subtitle lang="tz" line="Yippie! The cow is shouting."/><subtitle lang="to" line="Yippie! The cow is shouting."/><subtitle lang="ug" line="Yippie! The cow is shouting."/><subtitle lang="vu" line="Yippie! The cow is shouting."/><subtitle lang="zm" line="Yippie! The cow is shouting."/><subtitle lang="zw" line="Yippie! The cow is shouting."/><subtitle lang="sco" line="Yippie! The cow is shouting."/>
				<subtitle lang="ae" line="Yippie! The cow is shouting."/>
			</subtitles>
    </line>
    <line words="&#x3084;&#x3063;&#x305F;&#x3041;&#x3063;&#x3066;&#x99AC;&#x304C;&#x3055;&#x3051;&#x3093;&#x3067;&#x3044;&#x308B;&#x3088;&#x3002;" start="192335" length="8196">
      <subtitles>
        <subtitle lang="en" line="Yippie! The cow is shouting."/>
      <subtitle lang="us" line="Yippie! The cow is shouting."/><subtitle lang="au" line="Yippie! The cow is shouting."/><subtitle lang="bz" line="Yippie! The cow is shouting."/><subtitle lang="jm" line="Yippie! The cow is shouting."/><subtitle lang="tt" line="Yippie! The cow is shouting."/><subtitle lang="gy" line="Yippie! The cow is shouting."/><subtitle lang="ag" line="Yippie! The cow is shouting."/><subtitle lang="dm" line="Yippie! The cow is shouting."/><subtitle lang="vc" line="Yippie! The cow is shouting."/><subtitle lang="bs" line="Yippie! The cow is shouting."/><subtitle lang="ca" line="Yippie! The cow is shouting."/><subtitle lang="bd" line="Yippie! The cow is shouting."/><subtitle lang="bw" line="Yippie! The cow is shouting."/><subtitle lang="fj" line="Yippie! The cow is shouting."/><subtitle lang="gm" line="Yippie! The cow is shouting."/><subtitle lang="gh" line="Yippie! The cow is shouting."/><subtitle lang="gy" line="Yippie! The cow is shouting."/><subtitle lang="ke" line="Yippie! The cow is shouting."/><subtitle lang="mt" line="Yippie! The cow is shouting."/><subtitle lang="mu" line="Yippie! The cow is shouting."/><subtitle lang="na" line="Yippie! The cow is shouting."/><subtitle lang="ng" line="Yippie! The cow is shouting."/><subtitle lang="pk" line="Yippie! The cow is shouting."/><subtitle lang="rw" line="Yippie! The cow is shouting."/><subtitle lang="ws" line="Yippie! The cow is shouting."/><subtitle lang="sl" line="Yippie! The cow is shouting."/><subtitle lang="sg" line="Yippie! The cow is shouting."/><subtitle lang="sb" line="Yippie! The cow is shouting."/><subtitle lang="za" line="Yippie! The cow is shouting."/><subtitle lang="tz" line="Yippie! The cow is shouting."/><subtitle lang="to" line="Yippie! The cow is shouting."/><subtitle lang="ug" line="Yippie! The cow is shouting."/><subtitle lang="vu" line="Yippie! The cow is shouting."/><subtitle lang="zm" line="Yippie! The cow is shouting."/><subtitle lang="zw" line="Yippie! The cow is shouting."/><subtitle lang="sco" line="Yippie! The cow is shouting."/>
				<subtitle lang="ae" line="Yippie! The cow is shouting."/>
			</subtitles>
    </line>
    <line words="&#x6CF3;&#x3044;&#x3067;&#x308B;&#x306E;&#x306F;&#x8AB0;&#xFF1F;" start="205653" length="8195">
      <subtitles>
        <subtitle lang="en" line="Who is swimming by?"/>
      <subtitle lang="us" line="Who is swimming by?"/><subtitle lang="au" line="Who is swimming by?"/><subtitle lang="bz" line="Who is swimming by?"/><subtitle lang="jm" line="Who is swimming by?"/><subtitle lang="tt" line="Who is swimming by?"/><subtitle lang="gy" line="Who is swimming by?"/><subtitle lang="ag" line="Who is swimming by?"/><subtitle lang="dm" line="Who is swimming by?"/><subtitle lang="vc" line="Who is swimming by?"/><subtitle lang="bs" line="Who is swimming by?"/><subtitle lang="ca" line="Who is swimming by?"/><subtitle lang="bd" line="Who is swimming by?"/><subtitle lang="bw" line="Who is swimming by?"/><subtitle lang="fj" line="Who is swimming by?"/><subtitle lang="gm" line="Who is swimming by?"/><subtitle lang="gh" line="Who is swimming by?"/><subtitle lang="gy" line="Who is swimming by?"/><subtitle lang="ke" line="Who is swimming by?"/><subtitle lang="mt" line="Who is swimming by?"/><subtitle lang="mu" line="Who is swimming by?"/><subtitle lang="na" line="Who is swimming by?"/><subtitle lang="ng" line="Who is swimming by?"/><subtitle lang="pk" line="Who is swimming by?"/><subtitle lang="rw" line="Who is swimming by?"/><subtitle lang="ws" line="Who is swimming by?"/><subtitle lang="sl" line="Who is swimming by?"/><subtitle lang="sg" line="Who is swimming by?"/><subtitle lang="sb" line="Who is swimming by?"/><subtitle lang="za" line="Who is swimming by?"/><subtitle lang="tz" line="Who is swimming by?"/><subtitle lang="to" line="Who is swimming by?"/><subtitle lang="ug" line="Who is swimming by?"/><subtitle lang="vu" line="Who is swimming by?"/><subtitle lang="zm" line="Who is swimming by?"/><subtitle lang="zw" line="Who is swimming by?"/><subtitle lang="sco" line="Who is swimming by?"/>
				<subtitle lang="ae" line="Who is swimming by?"/>
			</subtitles>
    </line>
    <line words="&#x3042;&#x3072;&#x308B;&#x304C;&#x6CF3;&#x3044;&#x3067;&#x308B;&#x3000;&#x3042;&#x3072;&#x308B;&#x304C;&#x6CF3;&#x3044;&#x3067;&#x308B;" start="214104" length="8708">
      <subtitles>
        <subtitle lang="en" line="The duck is swimming by, the duck is swimming by."/>
      <subtitle lang="us" line="The duck is swimming by, the duck is swimming by."/><subtitle lang="au" line="The duck is swimming by, the duck is swimming by."/><subtitle lang="bz" line="The duck is swimming by, the duck is swimming by."/><subtitle lang="jm" line="The duck is swimming by, the duck is swimming by."/><subtitle lang="tt" line="The duck is swimming by, the duck is swimming by."/><subtitle lang="gy" line="The duck is swimming by, the duck is swimming by."/><subtitle lang="ag" line="The duck is swimming by, the duck is swimming by."/><subtitle lang="dm" line="The duck is swimming by, the duck is swimming by."/><subtitle lang="vc" line="The duck is swimming by, the duck is swimming by."/><subtitle lang="bs" line="The duck is swimming by, the duck is swimming by."/><subtitle lang="ca" line="The duck is swimming by, the duck is swimming by."/><subtitle lang="bd" line="The duck is swimming by, the duck is swimming by."/><subtitle lang="bw" line="The duck is swimming by, the duck is swimming by."/><subtitle lang="fj" line="The duck is swimming by, the duck is swimming by."/><subtitle lang="gm" line="The duck is swimming by, the duck is swimming by."/><subtitle lang="gh" line="The duck is swimming by, the duck is swimming by."/><subtitle lang="gy" line="The duck is swimming by, the duck is swimming by."/><subtitle lang="ke" line="The duck is swimming by, the duck is swimming by."/><subtitle lang="mt" line="The duck is swimming by, the duck is swimming by."/><subtitle lang="mu" line="The duck is swimming by, the duck is swimming by."/><subtitle lang="na" line="The duck is swimming by, the duck is swimming by."/><subtitle lang="ng" line="The duck is swimming by, the duck is swimming by."/><subtitle lang="pk" line="The duck is swimming by, the duck is swimming by."/><subtitle lang="rw" line="The duck is swimming by, the duck is swimming by."/><subtitle lang="ws" line="The duck is swimming by, the duck is swimming by."/><subtitle lang="sl" line="The duck is swimming by, the duck is swimming by."/><subtitle lang="sg" line="The duck is swimming by, the duck is swimming by."/><subtitle lang="sb" line="The duck is swimming by, the duck is swimming by."/><subtitle lang="za" line="The duck is swimming by, the duck is swimming by."/><subtitle lang="tz" line="The duck is swimming by, the duck is swimming by."/><subtitle lang="to" line="The duck is swimming by, the duck is swimming by."/><subtitle lang="ug" line="The duck is swimming by, the duck is swimming by."/><subtitle lang="vu" line="The duck is swimming by, the duck is swimming by."/><subtitle lang="zm" line="The duck is swimming by, the duck is swimming by."/><subtitle lang="zw" line="The duck is swimming by, the duck is swimming by."/><subtitle lang="sco" line="The duck is swimming by, the duck is swimming by."/>
				<subtitle lang="ae" line="The duck is swimming by, the duck is swimming by."/>
			</subtitles>
    </line>
    <line words="&#x3084;&#x3063;&#x305F;&#x3041;&#x3063;&#x3066;&#x3042;&#x3072;&#x308B;&#x304C;&#x3055;&#x3051;&#x3093;&#x3067;&#x3044;&#x308B;&#x3088;&#x3002;" start="223324" length="7939">
      <subtitles>
        <subtitle lang="en" line="Yippie! The duck is shouting."/>
      <subtitle lang="us" line="Yippie! The duck is shouting."/><subtitle lang="au" line="Yippie! The duck is shouting."/><subtitle lang="bz" line="Yippie! The duck is shouting."/><subtitle lang="jm" line="Yippie! The duck is shouting."/><subtitle lang="tt" line="Yippie! The duck is shouting."/><subtitle lang="gy" line="Yippie! The duck is shouting."/><subtitle lang="ag" line="Yippie! The duck is shouting."/><subtitle lang="dm" line="Yippie! The duck is shouting."/><subtitle lang="vc" line="Yippie! The duck is shouting."/><subtitle lang="bs" line="Yippie! The duck is shouting."/><subtitle lang="ca" line="Yippie! The duck is shouting."/><subtitle lang="bd" line="Yippie! The duck is shouting."/><subtitle lang="bw" line="Yippie! The duck is shouting."/><subtitle lang="fj" line="Yippie! The duck is shouting."/><subtitle lang="gm" line="Yippie! The duck is shouting."/><subtitle lang="gh" line="Yippie! The duck is shouting."/><subtitle lang="gy" line="Yippie! The duck is shouting."/><subtitle lang="ke" line="Yippie! The duck is shouting."/><subtitle lang="mt" line="Yippie! The duck is shouting."/><subtitle lang="mu" line="Yippie! The duck is shouting."/><subtitle lang="na" line="Yippie! The duck is shouting."/><subtitle lang="ng" line="Yippie! The duck is shouting."/><subtitle lang="pk" line="Yippie! The duck is shouting."/><subtitle lang="rw" line="Yippie! The duck is shouting."/><subtitle lang="ws" line="Yippie! The duck is shouting."/><subtitle lang="sl" line="Yippie! The duck is shouting."/><subtitle lang="sg" line="Yippie! The duck is shouting."/><subtitle lang="sb" line="Yippie! The duck is shouting."/><subtitle lang="za" line="Yippie! The duck is shouting."/><subtitle lang="tz" line="Yippie! The duck is shouting."/><subtitle lang="to" line="Yippie! The duck is shouting."/><subtitle lang="ug" line="Yippie! The duck is shouting."/><subtitle lang="vu" line="Yippie! The duck is shouting."/><subtitle lang="zm" line="Yippie! The duck is shouting."/><subtitle lang="zw" line="Yippie! The duck is shouting."/><subtitle lang="sco" line="Yippie! The duck is shouting."/>
				<subtitle lang="ae" line="Yippie! The duck is shouting."/>
			</subtitles>
    </line>
    <line words="&#x3084;&#x3063;&#x305F;&#x3041;&#x3063;&#x3066;&#x99AC;&#x304C;&#x3055;&#x3051;&#x3093;&#x3067;&#x3044;&#x308B;&#x3088;&#x3002;" start="232032" length="8195">
      <subtitles>
        <subtitle lang="en" line="Yippie! The duck is shouting."/>
      <subtitle lang="us" line="Yippie! The duck is shouting."/><subtitle lang="au" line="Yippie! The duck is shouting."/><subtitle lang="bz" line="Yippie! The duck is shouting."/><subtitle lang="jm" line="Yippie! The duck is shouting."/><subtitle lang="tt" line="Yippie! The duck is shouting."/><subtitle lang="gy" line="Yippie! The duck is shouting."/><subtitle lang="ag" line="Yippie! The duck is shouting."/><subtitle lang="dm" line="Yippie! The duck is shouting."/><subtitle lang="vc" line="Yippie! The duck is shouting."/><subtitle lang="bs" line="Yippie! The duck is shouting."/><subtitle lang="ca" line="Yippie! The duck is shouting."/><subtitle lang="bd" line="Yippie! The duck is shouting."/><subtitle lang="bw" line="Yippie! The duck is shouting."/><subtitle lang="fj" line="Yippie! The duck is shouting."/><subtitle lang="gm" line="Yippie! The duck is shouting."/><subtitle lang="gh" line="Yippie! The duck is shouting."/><subtitle lang="gy" line="Yippie! The duck is shouting."/><subtitle lang="ke" line="Yippie! The duck is shouting."/><subtitle lang="mt" line="Yippie! The duck is shouting."/><subtitle lang="mu" line="Yippie! The duck is shouting."/><subtitle lang="na" line="Yippie! The duck is shouting."/><subtitle lang="ng" line="Yippie! The duck is shouting."/><subtitle lang="pk" line="Yippie! The duck is shouting."/><subtitle lang="rw" line="Yippie! The duck is shouting."/><subtitle lang="ws" line="Yippie! The duck is shouting."/><subtitle lang="sl" line="Yippie! The duck is shouting."/><subtitle lang="sg" line="Yippie! The duck is shouting."/><subtitle lang="sb" line="Yippie! The duck is shouting."/><subtitle lang="za" line="Yippie! The duck is shouting."/><subtitle lang="tz" line="Yippie! The duck is shouting."/><subtitle lang="to" line="Yippie! The duck is shouting."/><subtitle lang="ug" line="Yippie! The duck is shouting."/><subtitle lang="vu" line="Yippie! The duck is shouting."/><subtitle lang="zm" line="Yippie! The duck is shouting."/><subtitle lang="zw" line="Yippie! The duck is shouting."/><subtitle lang="sco" line="Yippie! The duck is shouting."/>
				<subtitle lang="ae" line="Yippie! The duck is shouting."/>
			</subtitles>
    </line>
  </lines>
</karaoke>
